django_magicadmin/__init__.py
django_magicadmin/admin.py
django_magicadmin/apps.py
django_magicadmin/forms.py
django_magicadmin/migrations/0001_initial.py
django_magicadmin/migrations/0002_magiclink_already_used_and_more.py
django_magicadmin/migrations/0003_alter_magiclink_expires_at_and_more.py
django_magicadmin/migrations/0004_magiclink_used_at_alter_magiclink_secret_identifier.py
django_magicadmin/migrations/__init__.py
django_magicadmin/models.py
django_magicadmin/static/magicadmin/css/magicadmin.css
django_magicadmin/templates/emails/magiclogin.html
django_magicadmin/templates/emails/magiclogin.txt
django_magicadmin/templates/login.html
django_magicadmin/tests/test_models.py
django_magicadmin/tests/test_views.py
django_magicadmin/urls.py
django_magicadmin/urls_testing.py
django_magicadmin/views.py
django_magicadmin-0.1.0.dist-info/WHEEL
django_magicadmin-0.1.0.dist-info/METADATA
django_magicadmin-0.1.0.dist-info/RECORD
