Metadata-Version: 2.1
Name: django-magicadmin
Version: 0.1.0
Summary: 
License: MIT
Keywords: django_magicadmin,django magic login,django app,django auth
Author: Vinicius Mesel
Author-email: me@vmesel.com
Requires-Python: >=3.10,<4.0
Classifier: License :: OSI Approved :: MIT License
Classifier: Programming Language :: Python :: 3
Classifier: Programming Language :: Python :: 3.10
Requires-Dist: Django (>=4.1.2,<5.0.0)
